gsvi/__init__.py
gsvi/catcodes.py
gsvi/connection.py
gsvi/related.py
gsvi/timeseries.py
gsvi-0.2.1.dist-info/LICENSE
gsvi-0.2.1.dist-info/METADATA
gsvi-0.2.1.dist-info/WHEEL
gsvi-0.2.1.dist-info/top_level.txt
gsvi-0.2.1.dist-info/RECORD
