Metadata-Version: 2.1
Name: gsvi
Version: 0.2.1
Summary: Interface for the Google Trends time-series widget
Home-page: https://github.com/APirchner/gsvi
Author: Andreas Pirchner
Author-email: andreas.pirchner1990@gmail.com
License: MIT
Download-URL: https://github.com/APirchner/gsvi/archive/v0.2.1.tar.gz
Keywords: Google Trends,search volume,google search volume
Platform: UNKNOWN
Requires-Python: >=3.7
Requires-Dist: pandas (>=0.25.0)
Requires-Dist: requests (>=2.12.0)
